Metadata-Version: 2.1
Name: papers-without-code
Version: 0.3.0
Summary: A package (and website) to automatically attempt to find the code associated with a paper.
Author-email: Eva Maxfield Brown <evamaxfieldbrown@gmail.com>
License: MIT License
Project-URL: Homepage, https://github.com/evamaxfield/papers-without-code
Project-URL: Bug Tracker, https://github.com/evamaxfield/papers-without-code/issues
Project-URL: Documentation, https://evamaxfield.github.io/papers-without-code
Project-URL: User Support, https://github.com/evamaxfield/papers-without-code/issues
Classifier: Development Status :: 4 - Beta
Classifier: Natural Language :: English
Classifier: Programming Language :: Python :: 3.8
Classifier: Programming Language :: Python :: 3.9
Classifier: Programming Language :: Python :: 3.10
Requires-Python: >=3.8
License-File: LICENSE
Requires-Dist: backoff (~=2.2)
Requires-Dist: beautifulsoup4 (~=4.11)
Requires-Dist: dataclasses-json (~=0.5)
Requires-Dist: flask (~=2.2)
Requires-Dist: ghapi (~=1.0)
Requires-Dist: keybert (~=0.7)
Requires-Dist: python-dotenv (~=0.21.0)
Requires-Dist: requests (~=2.28)
Requires-Dist: semanticscholar (~=0.3)
Requires-Dist: sentence-transformers (~=2.2)
Provides-Extra: dev
Requires-Dist: ipython (>=8.4.0) ; extra == 'dev'
Provides-Extra: docs
Requires-Dist: m2r2 (>=0.2.7) ; extra == 'docs'
Requires-Dist: Sphinx (>=4.0.0) ; extra == 'docs'
Requires-Dist: furo (>=2022.4.7) ; extra == 'docs'
Requires-Dist: numpydoc ; extra == 'docs'
Requires-Dist: sphinx-copybutton ; extra == 'docs'
Requires-Dist: docutils (<0.19,>=0.18) ; extra == 'docs'
Requires-Dist: jupyterlab ; extra == 'docs'
Requires-Dist: nbconvert ; extra == 'docs'
Requires-Dist: seaborn ; extra == 'docs'
Provides-Extra: grobid
Requires-Dist: docker (~=6.0) ; extra == 'grobid'
Requires-Dist: grobid-client-python (==0.0.4) ; extra == 'grobid'
Requires-Dist: pandas (~=1.0) ; extra == 'grobid'
Requires-Dist: xmltodict (~=0.13) ; extra == 'grobid'
Provides-Extra: lint
Requires-Dist: black (>=22.3.0) ; extra == 'lint'
Requires-Dist: check-manifest (>=0.48) ; extra == 'lint'
Requires-Dist: flake8 (>=5.0.4) ; extra == 'lint'
Requires-Dist: flake8-debugger (>=3.2.1) ; extra == 'lint'
Requires-Dist: Flake8-pyproject (>=1.1.0) ; extra == 'lint'
Requires-Dist: flake8-typing-imports (>=1.9.0) ; extra == 'lint'
Requires-Dist: isort (>=5.7.0) ; extra == 'lint'
Requires-Dist: mypy (>=0.790) ; extra == 'lint'
Requires-Dist: pre-commit (>=2.20.0) ; extra == 'lint'
Requires-Dist: types-requests (~=2.28) ; extra == 'lint'
Provides-Extra: test
Requires-Dist: coverage (>=5.1) ; extra == 'test'
Requires-Dist: pytest (>=5.4.3) ; extra == 'test'
Requires-Dist: pytest-cov (>=2.9.0) ; extra == 'test'
Requires-Dist: pytest-raises (>=0.11) ; extra == 'test'
